[
    {
        "serial": "FOC2334T35J",
        "last_macsuck": "2024-02-22 10:20:34.444995",
        "pae_is_enabled": 0,
        "os_ver": "16.12.7",
        "snmp_comm": "public",
        "contact": "t2oper@roma1.infn.it",
        "first_seen_stamp": "2023-03-14 10:40",
        "ps2_type": null,
        "uptime_age": "2 months 30 days 00:18:26",
        "ps1_status": null,
        "location": "Tier 2",
        "creation": "2023-03-14 10:40:58.688246",
        "since_last_arpnip": 1372.742738,
        "layers": "00000110",
        "num_ports": 92,
        "ip": "172.25.25.2",
        "last_macsuck_stamp": "2024-02-22 10:20",
        "last_discover": "2024-02-12 12:30:44.103982",
        "since_first_seen": 29205159.464835,
        "fan": "Switch 1 - FAN - T1 1, Normal: normal, Switch 1 - FAN - T1 2, Normal: normal, Switch 1 - FAN - T1 3, Normal: normal, Switch 1 - FAN - T1 4, Normal: normal, Switch 1 - FAN - T1 5, Normal: normal",
        "log": null,
        "custom_fields": "{}",
        "dns": "3850-t2.roma1.infn.it",
        "slots": null,
        "last_arpnip": "2024-02-22 10:50:45.410343",
        "ps2_status": null,
        "os": "ios-xe",
        "is_pseudo": 0,
        "since_last_macsuck": 3183.708086,
        "uptime": 769070656,
        "snmp_engineid": "800000090300f4bd9e825180",
        "tags": [],
        "vtp_domain": "",
        "mac": "f4:bd:9e:82:51:80",
        "last_arpnip_stamp": "2024-02-22 10:50",
        "description": "Cisco IOS Software [Gibraltar], Catalyst L3 Switch Software (CAT3K_CAA-UNIVERSALK9-M), Version 16.12.7, RELEASE SOFTWARE (fc2)\r\nTechnical Support: http://www.cisco.com/techsupport\r\nCopyright (c) 1986-2022 by Cisco Systems, Inc.\r\nCompiled Wed 02-Feb-22 07:",
        "snmp_ver": 2,
        "ps1_type": null,
        "model": "38xxstack",
        "chassis_id": "",
        "since_last_discover": 859374.049099,
        "snmp_class": "SNMP::Info::Layer3::C4000",
        "last_discover_stamp": "2024-02-12 12:30",
        "name": "3850-t2.roma1.infn.it",
        "vendor": "cisco"
    },
    {
        "last_macsuck_stamp": "2024-02-22 10:20",
        "ip": "172.25.25.1",
        "since_first_seen": 29203127.859395,
        "last_discover": "2024-02-22 07:06:27.978684",
        "num_ports": 21,
        "creation": "2023-03-14 11:14:50.293686",
        "layers": "00000110",
        "since_last_arpnip": 1357.484081,
        "uptime_age": "3 months 8 days 18:57:15",
        "location": "Tier 2",
        "ps1_status": null,
        "contact": "t2oper@roma1.infn.it",
        "first_seen_stamp": "2023-03-14 11:14",
        "ps2_type": null,
        "snmp_comm": "public",
        "last_macsuck": "2024-02-22 10:20:50.806497",
        "os_ver": "15.1R7-S13",
        "pae_is_enabled": 0,
        "serial": "LX0214369883",
        "name": "ex4550-t2",
        "since_last_discover": 14830.174397,
        "snmp_class": "SNMP::Info::Layer3::Juniper",
        "last_discover_stamp": "2024-02-22 07:06",
        "vendor": "juniper",
        "chassis_id": "",
        "model": "EX4550-32F",
        "ps1_type": null,
        "mac": "cc:e1:7f:86:73:81",
        "last_arpnip_stamp": "2024-02-22 10:51",
        "description": "Juniper Networks, Inc. ex4550-32f Ethernet Switch, kernel JUNOS 15.1R7-S13, Build date: 2022-06-01 08:48:50 UTC Copyright (c) 1996-2022 Juniper Networks, Inc.",
        "snmp_ver": 2,
        "tags": [],
        "vtp_domain": null,
        "uptime": 853543519,
        "snmp_engineid": "80000a4c01ac191901",
        "is_pseudo": 0,
        "os": "junos",
        "ps2_status": null,
        "since_last_macsuck": 3167.346584,
        "last_arpnip": "2024-02-22 10:51:00.669",
        "slots": null,
        "dns": "4550-t2.roma1.infn.it",
        "custom_fields": "{}",
        "fan": null,
        "log": null
    },
    {
        "num_ports": 58,
        "last_macsuck_stamp": "2024-02-12 12:21",
        "ip": "172.24.24.2",
        "since_first_seen": 1462309.80273,
        "last_discover": "2024-02-09 07:06:14.769647",
        "uptime_age": "1 year 4 months 18 days 21:53:26",
        "location": "Tier 2",
        "ps1_status": "ok",
        "creation": "2024-02-05 13:01:48.350351",
        "layers": "00000110",
        "since_last_arpnip": 253348.435227,
        "snmp_comm": "public",
        "contact": "t2oper@roma1.infn.it",
        "first_seen_stamp": "2024-02-05 13:01",
        "ps2_type": "externalPS",
        "serial": "FCW2305A0L6",
        "last_macsuck": "2024-02-12 12:21:54.470589",
        "os_ver": "15.2(2)E7",
        "pae_is_enabled": 0,
        "chassis_id": "",
        "ps1_type": "other",
        "model": "29xxStack",
        "name": "swatlas-01.roma1.infn.it",
        "since_last_discover": 1138043.383434,
        "last_discover_stamp": "2024-02-09 07:06",
        "snmp_class": "SNMP::Info::Layer3::C6500",
        "vendor": "cisco",
        "tags": [],
        "vtp_domain": "",
        "mac": "00:87:64:37:be:40",
        "last_arpnip_stamp": "2024-02-19 12:51",
        "description": "Cisco IOS Software, C2960X Software (C2960X-UNIVERSALK9-M), Version 15.2(2)E7, RELEASE SOFTWARE (fc3)\r\nTechnical Support: http://www.cisco.com/techsupport\r\nCopyright (c) 1986-2017 by Cisco Systems, Inc.\r\nCompiled Wed 12-Jul-17 13:06 by prod_rel_team",
        "snmp_ver": 2,
        "is_pseudo": 0,
        "os": "ios",
        "ps2_status": "other",
        "since_last_macsuck": 859903.682492,
        "uptime": 4353800692,
        "snmp_engineid": "80000009030000876437be01",
        "custom_fields": "{}",
        "log": null,
        "fan": "ok",
        "last_arpnip": "2024-02-19 12:51:09.717854",
        "slots": 9,
        "dns": "swatlas-01.roma1.infn.it"
    },
    {
        "first_seen_stamp": "2023-03-14 10:41",
        "ps2_type": null,
        "contact": "t2oper@roma1.infn.it",
        "snmp_comm": "public",
        "os_ver": "S4510G-CMW520-R2202P18-S168",
        "pae_is_enabled": 0,
        "last_macsuck": "2024-02-22 10:21:22.261374",
        "serial": "AH505XT",
        "since_first_seen": 29205149.929078,
        "last_discover": "2024-02-22 07:06:41.620588",
        "last_macsuck_stamp": "2024-02-22 10:21",
        "ip": "172.24.24.3",
        "num_ports": 58,
        "layers": "01001110",
        "since_last_arpnip": 1360.851671,
        "creation": "2023-03-14 10:41:08.224003",
        "location": "Tier 2",
        "ps1_status": null,
        "uptime_age": "1 year 9 months 2 days 12:13:05",
        "snmp_engineid": "8000002b034001c6548d41",
        "uptime": 5533998518,
        "since_last_macsuck": 3135.891707,
        "is_pseudo": 0,
        "os": "3Com",
        "ps2_status": null,
        "last_arpnip": "2024-02-22 10:50:57.30141",
        "dns": "swatlas-02.roma1.infn.it",
        "slots": null,
        "custom_fields": "{}",
        "log": null,
        "fan": null,
        "vendor": "3com",
        "name": "swatlas-02",
        "since_last_discover": 14816.532493,
        "snmp_class": "SNMP::Info::Layer2::3Com",
        "last_discover_stamp": "2024-02-22 07:06",
        "chassis_id": "",
        "ps1_type": null,
        "model": "Switch 4510G 48-Port",
        "description": "Switch 4510G 48-Port Software Version 5.20 Release 2202P18",
        "last_arpnip_stamp": "2024-02-22 10:50",
        "snmp_ver": 2,
        "mac": null,
        "vtp_domain": null,
        "tags": []
    },
    {
        "uptime": 5549334858,
        "snmp_engineid": "8000002b03001ac1d334c1",
        "is_pseudo": 0,
        "ps2_status": null,
        "os": "3Com",
        "since_last_macsuck": 3142.982341,
        "last_arpnip": "2024-02-22 10:50:59.2647",
        "slots": null,
        "dns": "swatlas-03.roma1.infn.it",
        "custom_fields": "{}",
        "log": null,
        "fan": null,
        "name": "swatlas-03",
        "snmp_class": "SNMP::Info::Layer2::3Com",
        "since_last_discover": 14829.236009,
        "last_discover_stamp": "2024-02-22 07:06",
        "vendor": "3com",
        "chassis_id": "",
        "ps1_type": null,
        "model": "3Com Switch 4500G 48-Port",
        "mac": null,
        "description": "3Com Switch 4500G 48-Port Software Version 3Com OS V5.02.00s56p12",
        "last_arpnip_stamp": "2024-02-22 10:50",
        "snmp_ver": 2,
        "tags": [],
        "vtp_domain": null,
        "contact": "t2oper@roma1.infn.it",
        "ps2_type": null,
        "first_seen_stamp": "2023-03-14 10:41",
        "snmp_comm": "public",
        "last_macsuck": "2024-02-22 10:21:15.17074",
        "os_ver": "5.02.00s56p12",
        "pae_is_enabled": 0,
        "serial": "YEWF8LKD33480",
        "ip": "172.24.24.4",
        "last_macsuck_stamp": "2024-02-22 10:21",
        "since_first_seen": 29205132.446056,
        "last_discover": "2024-02-22 07:06:28.917072",
        "num_ports": 60,
        "creation": "2023-03-14 10:41:25.707025",
        "layers": "01001110",
        "since_last_arpnip": 1358.888381,
        "uptime_age": "1 year 9 months 4 days 06:49:08",
        "location": "Tier 2",
        "ps1_status": null
    },
    {
        "vtp_domain": null,
        "tags": [],
        "description": "3Com Switch 4500G 48-Port Software Version 3Com OS V5.02.00s56p12",
        "last_arpnip_stamp": "2024-02-22 10:50",
        "snmp_ver": 2,
        "mac": null,
        "chassis_id": "",
        "model": "3Com Switch 4500G 48-Port",
        "ps1_type": null,
        "vendor": "3com",
        "name": "swatlas-04",
        "snmp_class": "SNMP::Info::Layer2::3Com",
        "since_last_discover": 14840.345978,
        "last_discover_stamp": "2024-02-22 07:06",
        "custom_fields": "{}",
        "fan": null,
        "log": null,
        "last_arpnip": "2024-02-22 10:50:51.471179",
        "dns": "swatlas-04.roma1.infn.it",
        "slots": null,
        "since_last_macsuck": 3172.793602,
        "is_pseudo": 0,
        "ps2_status": null,
        "os": "3Com",
        "snmp_engineid": "8000002b03002473df5e41",
        "uptime": 5583775026,
        "location": "Tier 2",
        "ps1_status": null,
        "uptime_age": "1 year 9 months 8 days 06:29:10",
        "layers": "01001110",
        "since_last_arpnip": 1366.681902,
        "creation": "2023-07-28 16:25:13.685754",
        "num_ports": 56,
        "since_first_seen": 17693304.467327,
        "last_discover": "2024-02-22 07:06:17.807103",
        "last_macsuck_stamp": "2024-02-22 10:20",
        "ip": "172.24.24.5",
        "serial": "YEWFC4PDF5E00",
        "os_ver": "5.02.00s56p12",
        "pae_is_enabled": 0,
        "last_macsuck": "2024-02-22 10:20:45.359479",
        "snmp_comm": "public",
        "ps2_type": null,
        "first_seen_stamp": "2023-07-28 16:25",
        "contact": "t2oper@roma1.infn.it"
    },
    {
        "chassis_id": "",
        "ps1_type": null,
        "model": "3Com Switch 4500G 48-Port",
        "name": "swatlas-05",
        "snmp_class": "SNMP::Info::Layer2::3Com",
        "since_last_discover": 14841.62722,
        "last_discover_stamp": "2024-02-22 07:06",
        "vendor": "3com",
        "tags": [],
        "vtp_domain": null,
        "mac": null,
        "description": "3Com Switch 4500G 48-Port Software Version 3Com OS V5.02.00s56p12",
        "last_arpnip_stamp": "2024-02-22 10:51",
        "snmp_ver": 2,
        "is_pseudo": 0,
        "ps2_status": null,
        "os": "3Com",
        "since_last_macsuck": 3129.696013,
        "uptime": 5095917615,
        "snmp_engineid": "8000002b0300186e3ec2c1",
        "custom_fields": "{}",
        "fan": null,
        "log": null,
        "last_arpnip": "2024-02-22 10:51:02.164238",
        "dns": "swatlas-05.roma1.infn.it",
        "slots": null,
        "num_ports": 56,
        "last_macsuck_stamp": "2024-02-22 10:21",
        "ip": "172.24.24.6",
        "since_first_seen": 29205115.940405,
        "last_discover": "2024-02-22 07:06:16.525861",
        "uptime_age": "1 year 7 months 12 days 19:19:36",
        "location": "Tier 2",
        "ps1_status": null,
        "creation": "2023-03-14 10:41:42.212676",
        "layers": "01001110",
        "since_last_arpnip": 1355.988843,
        "snmp_comm": "public",
        "contact": "t2oper@roma1.infn.it",
        "first_seen_stamp": "2023-03-14 10:41",
        "ps2_type": null,
        "serial": "YEWF7KJ3EC280",
        "last_macsuck": "2024-02-22 10:21:28.457068",
        "os_ver": "5.02.00s56p12",
        "pae_is_enabled": 0
    },
    {
        "description": "HP J9147A 2910al-48G Switch, revision W.15.13.0005, ROM W.14.06 (/ws/swbuildm/W_rel_laredo_qaoff/code/build/sbm(swbuildm_W_rel_laredo_qaoff_rel_laredo)) (Formerly ProCurve)",
        "last_arpnip_stamp": null,
        "snmp_ver": 2,
        "mac": "c8:cb:b8:df:4b:c0",
        "vtp_domain": null,
        "tags": [],
        "vendor": "hp",
        "since_last_discover": 14814.754332,
        "last_discover_stamp": "2024-02-22 07:06",
        "snmp_class": "SNMP::Info::Layer2::HP",
        "name": "swatlas-06",
        "ps1_type": null,
        "model": "2910al-48G",
        "chassis_id": "",
        "slots": null,
        "dns": "swatlas-06.roma1.infn.it",
        "last_arpnip": null,
        "fan": "good",
        "log": null,
        "custom_fields": "{}",
        "snmp_engineid": "0000000b0000c8cbb8df4bc0",
        "uptime": 5590067090,
        "since_last_macsuck": 3148.979621,
        "ps2_status": "good",
        "os": "hp",
        "is_pseudo": 0,
        "since_last_arpnip": null,
        "layers": "01001010",
        "creation": "2023-03-14 10:41:04.807667",
        "ps1_status": "good",
        "location": "Tier 2",
        "uptime_age": "1 year 9 months 8 days 23:57:50",
        "last_discover": "2024-02-22 07:06:43.398749",
        "since_first_seen": 29205153.345414,
        "ip": "172.24.24.19",
        "last_macsuck_stamp": "2024-02-22 10:21",
        "num_ports": 56,
        "pae_is_enabled": 0,
        "os_ver": "W.15.13.0005",
        "last_macsuck": "2024-02-22 10:21:09.17346",
        "serial": "SG239IR0N2",
        "first_seen_stamp": "2023-03-14 10:41",
        "ps2_type": null,
        "contact": "t2oper@roma1.infn.it",
        "snmp_comm": "public"
    },
    {
        "serial": "TC3721411889",
        "pae_is_enabled": 0,
        "os_ver": "18.1R3-S6.1",
        "last_macsuck": "2024-02-22 10:21:22.647004",
        "snmp_comm": "public",
        "first_seen_stamp": "2023-10-10 11:40",
        "ps2_type": null,
        "contact": "t2oper@roma1.infn.it",
        "ps1_status": null,
        "location": "Tier 2",
        "uptime_age": "6 months 27 days 16:52:49",
        "since_last_arpnip": 1357.329281,
        "layers": "00000110",
        "creation": "2023-10-10 11:40:44.306208",
        "num_ports": 63,
        "last_discover": "2024-02-22 07:06:48.218338",
        "since_first_seen": 11403173.846873,
        "last_macsuck_stamp": "2024-02-22 10:21",
        "ip": "172.24.24.22",
        "fan": null,
        "log": null,
        "custom_fields": "{}",
        "slots": null,
        "dns": "swatlas-07.roma1.infn.it",
        "last_arpnip": "2024-02-22 10:51:00.8238",
        "since_last_macsuck": 3135.506077,
        "os": "junos",
        "ps2_status": null,
        "is_pseudo": 0,
        "snmp_engineid": "80000a4c0368228ec8ca00",
        "uptime": 1803196903,
        "vtp_domain": null,
        "tags": [],
        "last_arpnip_stamp": "2024-02-22 10:51",
        "description": "Juniper Networks, Inc. ex4600-40f Ethernet Switch, kernel JUNOS 18.1R3-S6.1, Build date: 2019-06-07 13:59:06 UTC Copyright (c) 1996-2019 Juniper Networks, Inc.",
        "snmp_ver": 2,
        "mac": "68:22:8e:c8:ca:02",
        "ps1_type": null,
        "model": "EX4600-40F",
        "chassis_id": "",
        "vendor": "juniper",
        "snmp_class": "SNMP::Info::Layer3::Juniper",
        "since_last_discover": 14809.934743,
        "last_discover_stamp": "2024-02-22 07:06",
        "name": "swatlas-07"
    },
    {
        "slots": null,
        "dns": "swatlas-ipmi-01.roma1.infn.it",
        "last_arpnip": "2024-02-22 10:50:47.406214",
        "fan": null,
        "log": null,
        "custom_fields": "{}",
        "snmp_engineid": "0000002b03000fcba26b1700",
        "uptime": 5589718763,
        "since_last_macsuck": 3177.457312,
        "ps2_status": null,
        "os": "3Com",
        "is_pseudo": 0,
        "snmp_ver": 2,
        "last_arpnip_stamp": "2024-02-22 10:50",
        "description": "3Com SuperStack 3 Switch 3870 48-port",
        "mac": null,
        "vtp_domain": null,
        "tags": [],
        "vendor": "3com",
        "snmp_class": "SNMP::Info::Layer2::3Com",
        "since_last_discover": 14863.99392,
        "last_discover_stamp": "2024-02-22 07:05",
        "name": "swatlas-ipmi-01",
        "ps1_type": null,
        "model": "3Com SuperStack 3 Switch 3870 48-port",
        "chassis_id": "",
        "pae_is_enabled": 1,
        "os_ver": null,
        "last_macsuck": "2024-02-22 10:20:40.695769",
        "serial": "77EF4EBA26B17",
        "first_seen_stamp": "2023-03-17 15:51",
        "ps2_type": null,
        "contact": "t2oper@roma1.infn.it",
        "snmp_comm": "public",
        "since_last_arpnip": 1370.746867,
        "layers": "00000111",
        "creation": "2023-03-17 15:51:03.461251",
        "ps1_status": null,
        "location": "Tier 2",
        "uptime_age": "1 year 9 months 8 days 22:59:47",
        "last_discover": "2024-02-22 07:05:54.159161",
        "since_first_seen": 28927354.69183,
        "ip": "172.24.24.9",
        "last_macsuck_stamp": "2024-02-22 10:20",
        "num_ports": 52
    },
    {
        "last_macsuck": "2024-02-22 10:20:55.403409",
        "pae_is_enabled": 0,
        "os_ver": "U.11.11",
        "serial": "CN049YV1KD",
        "contact": "t2oper@roma1.infn.it",
        "first_seen_stamp": "2023-03-14 11:10",
        "ps2_type": null,
        "snmp_comm": "public",
        "creation": "2023-03-14 11:10:01.332289",
        "since_last_arpnip": null,
        "layers": "01001010",
        "uptime_age": "6 months 25 days 00:45:55",
        "ps1_status": "good",
        "location": "Tier 2",
        "ip": "172.24.24.15",
        "last_macsuck_stamp": "2024-02-22 10:20",
        "last_discover": "2024-02-22 07:06:51.511436",
        "since_first_seen": 29203416.820792,
        "num_ports": 58,
        "dns": "swatlas-ipmi-04.roma1.infn.it",
        "slots": null,
        "last_arpnip": null,
        "log": null,
        "fan": "good",
        "custom_fields": "{}",
        "uptime": 1780115520,
        "snmp_engineid": "0000000b0000b439d6178800",
        "os": "hp",
        "ps2_status": "notPresent",
        "is_pseudo": 0,
        "since_last_macsuck": 3162.749672,
        "mac": "b4:39:d6:17:88:00",
        "description": "ProCurve j9020a Switch 2510-48, revision U.11.11, ROM R.10.06 (/sw/code/build/dosx(ndx))",
        "last_arpnip_stamp": null,
        "snmp_ver": 2,
        "tags": [],
        "vtp_domain": null,
        "snmp_class": "SNMP::Info::Layer2::HP",
        "since_last_discover": 14806.641645,
        "last_discover_stamp": "2024-02-22 07:06",
        "name": "swatlas-ipmi-04",
        "vendor": "hp",
        "ps1_type": null,
        "model": "2510-48A",
        "chassis_id": ""
    },
    {
        "tags": [],
        "vtp_domain": null,
        "mac": null,
        "snmp_ver": 2,
        "last_arpnip_stamp": "2024-02-22 10:50",
        "description": "Switch 4510G 48-Port Software Version 5.20 Release 2202P18",
        "model": "Switch 4510G 48-Port",
        "ps1_type": null,
        "chassis_id": "",
        "since_last_discover": 14830.423408,
        "snmp_class": "SNMP::Info::Layer2::3Com",
        "last_discover_stamp": "2024-02-22 07:06",
        "name": "swcms-01",
        "vendor": "3com",
        "fan": null,
        "log": null,
        "custom_fields": "{}",
        "slots": null,
        "dns": "swcms-01.roma1.infn.it",
        "last_arpnip": "2024-02-22 10:50:54.90677",
        "os": "3Com",
        "ps2_status": null,
        "is_pseudo": 0,
        "since_last_macsuck": 3131.672581,
        "uptime": 5540046489,
        "snmp_engineid": "8000002b034001c6bca741",
        "uptime_age": "1 year 9 months 3 days 05:01:04",
        "ps1_status": null,
        "location": "Tier 2",
        "creation": "2023-03-14 10:41:06.137197",
        "since_last_arpnip": 1363.246311,
        "layers": "01001110",
        "num_ports": 56,
        "last_macsuck_stamp": "2024-02-22 10:21",
        "ip": "172.24.24.7",
        "last_discover": "2024-02-22 07:06:27.729673",
        "since_first_seen": 29205152.015884,
        "serial": "UJP08NP",
        "last_macsuck": "2024-02-22 10:21:26.4805",
        "pae_is_enabled": 0,
        "os_ver": "S4510G-CMW520-R2202P18-S168",
        "snmp_comm": "public",
        "contact": "t2oper@roma1.infn.it",
        "first_seen_stamp": "2023-03-14 10:41",
        "ps2_type": null
    },
    {
        "layers": "00000110",
        "since_last_arpnip": 238964.875758,
        "creation": "2023-03-14 10:41:21.285239",
        "location": "Tier 2",
        "ps1_status": "ok",
        "uptime_age": "1 year 8 months 25 days 23:05:08",
        "since_first_seen": 29205136.867842,
        "last_discover": "2024-02-09 07:05:33.0601",
        "ip": "172.24.24.8",
        "last_macsuck_stamp": "2024-02-19 16:21",
        "num_ports": 58,
        "os_ver": "15.2(2)E7",
        "pae_is_enabled": 0,
        "last_macsuck": "2024-02-19 16:21:44.28082",
        "serial": "FCW2305A0HN",
        "first_seen_stamp": "2023-03-14 10:41",
        "ps2_type": "externalPS",
        "contact": "t2oper@roma1.infn.it",
        "snmp_comm": "public",
        "description": "Cisco IOS Software, C2960X Software (C2960X-UNIVERSALK9-M), Version 15.2(2)E7, RELEASE SOFTWARE (fc3)\r\nTechnical Support: http://www.cisco.com/techsupport\r\nCopyright (c) 1986-2017 by Cisco Systems, Inc.\r\nCompiled Wed 12-Jul-17 13:06 by prod_rel_team",
        "last_arpnip_stamp": "2024-02-19 16:50",
        "snmp_ver": 2,
        "mac": "00:77:8d:77:ce:c0",
        "vtp_domain": "",
        "tags": [],
        "vendor": "cisco",
        "name": "swcms-02.roma1.infn.it",
        "since_last_discover": 1138085.092981,
        "last_discover_stamp": "2024-02-09 07:05",
        "snmp_class": "SNMP::Info::Layer3::C6500",
        "chassis_id": "",
        "ps1_type": "other",
        "model": "29xxStack",
        "last_arpnip": "2024-02-19 16:50:53.277323",
        "dns": "swcms-02.roma1.infn.it",
        "slots": 9,
        "custom_fields": "{}",
        "fan": "ok",
        "log": null,
        "snmp_engineid": "80000009030000778d77ce81",
        "uptime": 5477430898,
        "since_last_macsuck": 240713.872261,
        "is_pseudo": 0,
        "ps2_status": "other",
        "os": "ios"
    },
    {
        "serial": "UL70DS2",
        "last_macsuck": "2024-02-22 10:20:52.569992",
        "pae_is_enabled": 0,
        "os_ver": "S4510G-CMW520-R2202P18-S168",
        "snmp_comm": "public",
        "contact": "t2oper@roma1.infn.it",
        "ps2_type": null,
        "first_seen_stamp": "2023-03-14 10:41",
        "uptime_age": "1 year 7 months 8 days 00:17:06",
        "ps1_status": null,
        "location": "Tier 2 ",
        "creation": "2023-03-14 10:41:12.23125",
        "since_last_arpnip": 1359.018177,
        "layers": "01001110",
        "num_ports": 56,
        "last_macsuck_stamp": "2024-02-22 10:20",
        "ip": "172.24.24.17",
        "last_discover": "2024-02-22 07:06:52.048482",
        "since_first_seen": 29205145.921831,
        "log": null,
        "fan": null,
        "custom_fields": "{}",
        "slots": null,
        "dns": "swcms-03.roma1.infn.it",
        "last_arpnip": "2024-02-22 10:50:59.134904",
        "ps2_status": null,
        "os": "3Com",
        "is_pseudo": 0,
        "since_last_macsuck": 3165.583089,
        "uptime": 5054502664,
        "snmp_engineid": "8000002b0320fdf1642741",
        "tags": [],
        "vtp_domain": null,
        "mac": null,
        "snmp_ver": 2,
        "last_arpnip_stamp": "2024-02-22 10:50",
        "description": "Switch 4510G 48-Port Software Version 5.20 Release 2202P18",
        "model": "Switch 4510G 48-Port",
        "ps1_type": null,
        "chassis_id": "",
        "since_last_discover": 14806.104599,
        "snmp_class": "SNMP::Info::Layer2::3Com",
        "last_discover_stamp": "2024-02-22 07:06",
        "name": "swcms-03",
        "vendor": "3com"
    },
    {
        "log": null,
        "fan": null,
        "custom_fields": "{}",
        "dns": "swcms-05.roma1.infn.it",
        "slots": null,
        "last_arpnip": "2024-02-22 10:50:48.925418",
        "os": "junos",
        "ps2_status": null,
        "is_pseudo": 0,
        "since_last_macsuck": 3149.828813,
        "uptime": 361188400,
        "snmp_engineid": "80000a4c0368228ec8d400",
        "tags": [],
        "vtp_domain": null,
        "mac": "68:22:8e:c8:d4:02",
        "last_arpnip_stamp": "2024-02-22 10:50",
        "snmp_ver": 2,
        "description": "Juniper Networks, Inc. ex4600-40f Ethernet Switch, kernel JUNOS 18.1R3-S6.1, Build date: 2019-06-07 13:59:06 UTC Copyright (c) 1996-2019 Juniper Networks, Inc.",
        "model": "EX4600-40F",
        "ps1_type": null,
        "chassis_id": "",
        "since_last_discover": 14819.939949,
        "last_discover_stamp": "2024-02-22 07:06",
        "snmp_class": "SNMP::Info::Layer3::Juniper",
        "name": "swcms-05",
        "vendor": "juniper",
        "serial": "TC3721411830",
        "last_macsuck": "2024-02-22 10:21:08.324268",
        "pae_is_enabled": 0,
        "os_ver": "18.1R3-S6.1",
        "snmp_comm": "public",
        "contact": "t2oper@roma1.infn.it",
        "first_seen_stamp": "2023-07-17 19:17",
        "ps2_type": null,
        "uptime_age": "1 month 10 days 19:18:04",
        "ps1_status": null,
        "location": "Tier 2",
        "creation": "2023-07-17 19:17:15.564454",
        "since_last_arpnip": 1369.227663,
        "layers": "00000110",
        "num_ports": 107,
        "last_macsuck_stamp": "2024-02-22 10:21",
        "ip": "172.24.24.23",
        "last_discover": "2024-02-22 07:06:38.213132",
        "since_first_seen": 18546982.588627
    },
    {
        "ps2_status": null,
        "os": "3Com",
        "is_pseudo": 0,
        "since_last_macsuck": 82278.942226,
        "uptime": 1228707973,
        "snmp_engineid": "",
        "log": null,
        "fan": null,
        "custom_fields": "{}",
        "slots": null,
        "dns": "swcms-ipmi-01.roma1.infn.it",
        "last_arpnip": null,
        "model": "3Com SuperStack 3",
        "ps1_type": null,
        "chassis_id": "",
        "snmp_class": "SNMP::Info::Layer2::3Com",
        "since_last_discover": 706034.182625,
        "last_discover_stamp": "2024-02-14 07:06",
        "name": "swcms-ipmi-01",
        "vendor": "3com",
        "tags": [],
        "vtp_domain": null,
        "mac": null,
        "last_arpnip_stamp": null,
        "snmp_ver": 1,
        "description": "3Com SuperStack 3",
        "snmp_comm": "public",
        "contact": "t2oper@roma1.infn.it",
        "ps2_type": null,
        "first_seen_stamp": "2023-03-17 14:55",
        "serial": "",
        "last_macsuck": "2024-02-21 12:22:19.210855",
        "pae_is_enabled": 0,
        "os_ver": null,
        "num_ports": 50,
        "last_macsuck_stamp": "2024-02-21 12:22",
        "ip": "172.24.24.12",
        "last_discover": "2024-02-14 07:06:23.970456",
        "since_first_seen": 28930688.856721,
        "uptime_age": "4 months 22 days 05:04:39",
        "ps1_status": null,
        "location": "Tier 2",
        "creation": "2023-03-17 14:55:29.29636",
        "since_last_arpnip": null,
        "layers": "00000010"
    },
    {
        "name": "swcms-ipmi-02",
        "last_discover_stamp": "2024-02-22 07:06",
        "since_last_discover": 14843.300128,
        "snmp_class": "SNMP::Info::Layer2::3Com",
        "vendor": "3com",
        "chassis_id": "",
        "ps1_type": null,
        "model": "3Com Switch 4500G 48-Port",
        "mac": null,
        "last_arpnip_stamp": "2024-02-22 10:50",
        "description": "3Com Switch 4500G 48-Port Software Version 3Com OS V5.02.00s56p12",
        "snmp_ver": 2,
        "tags": [],
        "vtp_domain": null,
        "uptime": 127302343,
        "snmp_engineid": "8000002b0300186e497ec1",
        "is_pseudo": 0,
        "os": "3Com",
        "ps2_status": null,
        "since_last_macsuck": 3152.321717,
        "last_arpnip": "2024-02-22 10:50:51.10015",
        "dns": "swcms-ipmi-02.roma1.infn.it",
        "slots": null,
        "custom_fields": "{}",
        "fan": null,
        "log": null,
        "last_macsuck_stamp": "2024-02-22 10:21",
        "ip": "172.24.24.13",
        "since_first_seen": 1196231.251945,
        "last_discover": "2024-02-22 07:06:14.852953",
        "num_ports": 56,
        "creation": "2024-02-08 14:56:26.901136",
        "layers": "01001110",
        "since_last_arpnip": 1367.052931,
        "uptime_age": "14 days 17:37:03",
        "location": "Tier 2",
        "ps1_status": null,
        "contact": "t2oper@roma1.infn.it",
        "ps2_type": null,
        "first_seen_stamp": "2024-02-08 14:56",
        "snmp_comm": "public",
        "last_macsuck": "2024-02-22 10:21:05.831364",
        "os_ver": "5.02.00s56p12",
        "pae_is_enabled": 0,
        "serial": "YEWF7UJ497E80"
    },
    {
        "log": null,
        "fan": null,
        "custom_fields": "{}",
        "dns": "swcms-ipmi-03.roma1.infn.it",
        "slots": null,
        "last_arpnip": "2024-02-22 10:50:45.194827",
        "os": "3Com",
        "ps2_status": null,
        "is_pseudo": 0,
        "since_last_macsuck": 3174.479931,
        "uptime": 5096678182,
        "snmp_engineid": "8000002b0300186e49a1c1",
        "tags": [],
        "vtp_domain": null,
        "mac": null,
        "last_arpnip_stamp": "2024-02-22 10:50",
        "snmp_ver": 2,
        "description": "3Com Switch 4500G 48-Port Software Version 3Com OS V5.01.00s56",
        "ps1_type": null,
        "model": "3Com Switch 4500G 48-Port",
        "chassis_id": "",
        "snmp_class": "SNMP::Info::Layer2::3Com",
        "since_last_discover": 14850.304794,
        "last_discover_stamp": "2024-02-22 07:06",
        "name": "swcms-ipmi-03",
        "vendor": "3com",
        "serial": "YEWF7UJ49A180",
        "last_macsuck": "2024-02-22 10:20:43.67315",
        "pae_is_enabled": 0,
        "os_ver": "5.01.00s56",
        "snmp_comm": "public",
        "contact": "t2oper@roma1.infn.it",
        "first_seen_stamp": "2023-03-17 15:00",
        "ps2_type": null,
        "uptime_age": "1 year 7 months 12 days 21:26:21",
        "ps1_status": null,
        "location": "Tier 2 ",
        "creation": "2023-03-17 15:00:24.224597",
        "since_last_arpnip": 1372.958254,
        "layers": "01001110",
        "num_ports": 56,
        "last_macsuck_stamp": "2024-02-22 10:20",
        "ip": "172.24.24.16",
        "last_discover": "2024-02-22 07:06:07.848287",
        "since_first_seen": 28930393.928484
    },
    {
        "is_pseudo": 0,
        "ps2_status": null,
        "os": "3Com",
        "since_last_macsuck": 3163.168189,
        "uptime": 5589706073,
        "snmp_engineid": "0000002b03000bac0911c000",
        "custom_fields": "{}",
        "log": null,
        "fan": null,
        "last_arpnip": null,
        "dns": "swcms-ipmi-04.roma1.infn.it",
        "slots": null,
        "chassis_id": "",
        "ps1_type": null,
        "model": "3Com SuperStack 3",
        "name": "swcms-ipmi-04",
        "since_last_discover": 14821.772225,
        "snmp_class": "SNMP::Info::Layer2::3Com",
        "last_discover_stamp": "2024-02-22 07:06",
        "vendor": "3com",
        "tags": [],
        "vtp_domain": null,
        "mac": null,
        "last_arpnip_stamp": null,
        "snmp_ver": 2,
        "description": "3Com SuperStack 3",
        "snmp_comm": "public",
        "contact": "t2oper@roma1.infn.it",
        "ps2_type": null,
        "first_seen_stamp": "2023-03-17 15:19",
        "serial": "",
        "last_macsuck": "2024-02-22 10:20:54.984892",
        "os_ver": null,
        "pae_is_enabled": 1,
        "num_ports": 36,
        "last_macsuck_stamp": "2024-02-22 10:20",
        "ip": "172.24.24.18",
        "since_first_seen": 28929247.700118,
        "last_discover": "2024-02-22 07:06:36.380856",
        "uptime_age": "1 year 9 months 8 days 22:57:40",
        "location": "Tier 2 ",
        "ps1_status": null,
        "creation": "2023-03-17 15:19:30.452963",
        "layers": "00000010",
        "since_last_arpnip": null
    },
    {
        "num_ports": 58,
        "ip": "172.24.24.21",
        "last_macsuck_stamp": "2024-02-19 15:22",
        "last_discover": "2024-02-09 07:06:20.138003",
        "since_first_seen": 29205132.708813,
        "uptime_age": "1 year 8 months 25 days 23:07:54",
        "ps1_status": "ok",
        "location": "Tier 2",
        "creation": "2023-03-14 10:41:25.444268",
        "since_last_arpnip": 850951.93463,
        "layers": "00000110",
        "snmp_comm": "public",
        "contact": "t2oper@roma1.infn.it",
        "first_seen_stamp": "2023-03-14 10:41",
        "ps2_type": "externalPS",
        "serial": "FCW2305A0L2",
        "last_macsuck": "2024-02-19 15:22:07.908616",
        "pae_is_enabled": 0,
        "os_ver": "15.2(2)E7",
        "model": "29xxStack",
        "ps1_type": "other",
        "chassis_id": "",
        "snmp_class": "SNMP::Info::Layer3::C6500",
        "since_last_discover": 1138038.015078,
        "last_discover_stamp": "2024-02-09 07:06",
        "name": "swcms-ipmi-05.roma1.infn.it",
        "vendor": "cisco",
        "tags": [],
        "vtp_domain": "",
        "mac": "00:87:64:37:d9:c0",
        "snmp_ver": 2,
        "last_arpnip_stamp": "2024-02-12 14:51",
        "description": "Cisco IOS Software, C2960X Software (C2960X-UNIVERSALK9-M), Version 15.2(2)E7, RELEASE SOFTWARE (fc3)\r\nTechnical Support: http://www.cisco.com/techsupport\r\nCopyright (c) 1986-2017 by Cisco Systems, Inc.\r\nCompiled Wed 12-Jul-17 13:06 by prod_rel_team",
        "os": "ios",
        "ps2_status": "other",
        "is_pseudo": 0,
        "since_last_macsuck": 244290.244465,
        "uptime": 5477447405,
        "snmp_engineid": "80000009030000876437d981",
        "log": null,
        "fan": "ok",
        "custom_fields": "{}",
        "dns": "swcms-ipmi-05.roma1.infn.it",
        "slots": 9,
        "last_arpnip": "2024-02-12 14:51:06.218451"
    },
    {
        "ip": "172.24.24.1",
        "last_macsuck_stamp": "2024-02-22 10:21",
        "last_discover": "2024-02-22 07:06:14.978977",
        "since_first_seen": 29203425.967034,
        "num_ports": 111,
        "creation": "2023-03-14 11:09:52.186047",
        "since_last_arpnip": 1366.934024,
        "layers": "00000110",
        "uptime_age": "1 year 9 months 8 days 23:26:50",
        "ps1_status": null,
        "location": "Tier 2",
        "contact": "t2oper@roma1.infn.it",
        "ps2_type": null,
        "first_seen_stamp": "2023-03-14 11:09",
        "snmp_comm": "public",
        "last_macsuck": "2024-02-22 10:21:30.193473",
        "pae_is_enabled": 0,
        "os_ver": "12.3R3.4",
        "serial": "BP0210485133",
        "since_last_discover": 14843.174104,
        "snmp_class": "SNMP::Info::Layer3::Juniper",
        "last_discover_stamp": "2024-02-22 07:06",
        "name": "sw-ex4200",
        "vendor": "juniper",
        "ps1_type": null,
        "model": "EX4200-48T",
        "chassis_id": "",
        "mac": "28:c0:da:3a:73:81",
        "snmp_ver": 2,
        "last_arpnip_stamp": "2024-02-22 10:50",
        "description": "Juniper Networks, Inc. ex4200-48t Ethernet Switch, kernel JUNOS 12.3R3.4, Build date: 2013-06-14 01:37:19 UTC Copyright (c) 1996-2013 Juniper Networks, Inc.",
        "tags": [],
        "vtp_domain": null,
        "uptime": 5589881049,
        "snmp_engineid": "80000a4c01ac181801",
        "os": "junos",
        "ps2_status": null,
        "is_pseudo": 0,
        "since_last_macsuck": 3127.959608,
        "slots": null,
        "dns": "sw-ex4200.roma1.infn.it",
        "last_arpnip": "2024-02-22 10:50:51.219057",
        "log": null,
        "fan": null,
        "custom_fields": "{}"
    }
]